<?xml version="1.0" encoding="UTF-8" standalone="yes"?>
<p:sld xmlns:a="http://schemas.openxmlformats.org/drawingml/2006/main" xmlns:r="http://schemas.openxmlformats.org/officeDocument/2006/relationships" xmlns:p="http://schemas.openxmlformats.org/presentationml/2006/main"><p:cSld><p:spTree><p:nvGrpSpPr><p:cNvPr id="1" name=""/><p:cNvGrpSpPr/><p:nvPr/></p:nvGrpSpPr><p:grpSpPr><a:xfrm><a:off x="0" y="0"/><a:ext cx="0" cy="0"/><a:chOff x="0" y="0"/><a:chExt cx="0" cy="0"/></a:xfrm></p:grpSpPr><p:sp><p:nvSpPr><p:cNvPr id="2" name="Title 1"/><p:cNvSpPr><a:spLocks noGrp="1"/></p:cNvSpPr><p:nvPr><p:ph type="title"/></p:nvPr></p:nvSpPr><p:spPr/><p:txBody><a:bodyPr/><a:lstStyle/><a:p><a:r><a:rPr lang="en-US" altLang="en-US" dirty="0"/><a:t>Representation</a:t></a:r><a:endParaRPr lang="en-US" dirty="0"/></a:p></p:txBody></p:sp><p:sp><p:nvSpPr><p:cNvPr id="3" name="Content Placeholder 2"/><p:cNvSpPr><a:spLocks noGrp="1"/></p:cNvSpPr><p:nvPr><p:ph idx="1"/></p:nvPr></p:nvSpPr><p:spPr><a:xfrm><a:off x="317863" y="4953000"/><a:ext cx="8915400" cy="1098550"/></a:xfrm></p:spPr><p:txBody><a:bodyPr/><a:lstStyle/><a:p><a:pPr marL="0" indent="0"><a:buNone/></a:pPr><a:r><a:rPr lang="en-US" dirty="0"/><a:t>v</a:t></a:r><a:r><a:rPr lang="en-US" dirty="0" smtClean="0"/><a:t> = a + b = 2.1</a:t></a:r><a:r><a:rPr lang="en-US" i="1" dirty="0" smtClean="0"/><a:t>i</a:t></a:r><a:r><a:rPr lang="en-US" dirty="0" smtClean="0"/><a:t> + 1.2</a:t></a:r><a:r><a:rPr lang="en-US" i="1" dirty="0" smtClean="0"/><a:t>j </a:t></a:r><a:r><a:rPr lang="en-US" dirty="0" smtClean="0"><a:sym typeface="Wingdings" panose="05000000000000000000" pitchFamily="2" charset="2"/></a:rPr><a:t> v = (2.1, 1.2)</a:t></a:r></a:p><a:p><a:pPr marL="0" indent="0"><a:buNone/></a:pPr><a:r><a:rPr lang="en-US" dirty="0" smtClean="0"><a:sym typeface="Wingdings" panose="05000000000000000000" pitchFamily="2" charset="2"/></a:rPr><a:t>P = O + OP = O + a + b = O + 3.9</a:t></a:r><a:r><a:rPr lang="en-US" i="1" dirty="0" smtClean="0"/><a:t>i</a:t></a:r><a:r><a:rPr lang="en-US" dirty="0" smtClean="0"/><a:t> </a:t></a:r><a:r><a:rPr lang="en-US" dirty="0"/><a:t>+ </a:t></a:r><a:r><a:rPr lang="en-US" dirty="0" smtClean="0"/><a:t>3.7</a:t></a:r><a:r><a:rPr lang="en-US" i="1" dirty="0" smtClean="0"/><a:t>j </a:t></a:r><a:r><a:rPr lang="en-US" dirty="0" smtClean="0"><a:sym typeface="Wingdings" panose="05000000000000000000" pitchFamily="2" charset="2"/></a:rPr><a:t> P = (3.9, 3.7)</a:t></a:r><a:r><a:rPr lang="en-US" dirty="0" smtClean="0"/><a:t> </a:t></a:r><a:endParaRPr lang="en-US" dirty="0"/></a:p></p:txBody></p:sp><p:cxnSp><p:nvCxnSpPr><p:cNvPr id="5" name="Straight Arrow Connector 4"/><p:cNvCxnSpPr/><p:nvPr/></p:nvCxnSpPr><p:spPr bwMode="auto"><a:xfrm><a:off x="457200" y="4038600"/><a:ext cx="3810000" cy="0"/></a:xfrm><a:prstGeom prst="straightConnector1"><a:avLst/></a:prstGeom><a:solidFill><a:schemeClr val="accent1"/></a:solidFill><a:ln w="44450" cap="flat" cmpd="sng" algn="ctr"><a:solidFill><a:schemeClr val="tx1"/></a:solidFill><a:prstDash val="solid"/><a:round/><a:headEnd type="none" w="med" len="med"/><a:tailEnd type="triangle"/></a:ln><a:effectLst/></p:spPr></p:cxnSp><p:cxnSp><p:nvCxnSpPr><p:cNvPr id="7" name="Straight Arrow Connector 6"/><p:cNvCxnSpPr/><p:nvPr/></p:nvCxnSpPr><p:spPr bwMode="auto"><a:xfrm flipV="1"><a:off x="914400" y="1066800"/><a:ext cx="0" cy="3429000"/></a:xfrm><a:prstGeom prst="straightConnector1"><a:avLst/></a:prstGeom><a:solidFill><a:schemeClr val="accent1"/></a:solidFill><a:ln w="44450" cap="flat" cmpd="sng" algn="ctr"><a:solidFill><a:schemeClr val="tx1"/></a:solidFill><a:prstDash val="solid"/><a:round/><a:headEnd type="none" w="med" len="med"/><a:tailEnd type="triangle"/></a:ln><a:effectLst/></p:spPr></p:cxnSp><p:cxnSp><p:nvCxnSpPr><p:cNvPr id="9" name="Straight Arrow Connector 8"/><p:cNvCxnSpPr/><p:nvPr/></p:nvCxnSpPr><p:spPr bwMode="auto"><a:xfrm><a:off x="914400" y="4038600"/><a:ext cx="533400" cy="0"/></a:xfrm><a:prstGeom prst="straightConnector1"><a:avLst/></a:prstGeom><a:solidFill><a:schemeClr val="accent1"/></a:solidFill><a:ln w="38100" cap="flat" cmpd="sng" algn="ctr"><a:solidFill><a:srgbClr val="FF0000"/></a:solidFill><a:prstDash val="solid"/><a:round/><a:headEnd type="none" w="med" len="med"/><a:tailEnd type="triangle"/></a:ln><a:effectLst/></p:spPr></p:cxnSp><p:cxnSp><p:nvCxnSpPr><p:cNvPr id="11" name="Straight Connector 10"/><p:cNvCxnSpPr/><p:nvPr/></p:nvCxnSpPr><p:spPr bwMode="auto"><a:xfrm><a:off x="1447800" y="1066800"/><a:ext cx="0" cy="3429000"/></a:xfrm><a:prstGeom prst="line"><a:avLst/></a:prstGeom><a:solidFill><a:schemeClr val="accent1"/></a:solidFill><a:ln w="9525" cap="flat" cmpd="sng" algn="ctr"><a:solidFill><a:schemeClr val="bg2"><a:lumMod val="75000"/></a:schemeClr></a:solidFill><a:prstDash val="dash"/><a:round/><a:headEnd type="none" w="med" len="med"/><a:tailEnd type="none" w="med" len="med"/></a:ln><a:effectLst/></p:spPr></p:cxnSp><p:cxnSp><p:nvCxnSpPr><p:cNvPr id="13" name="Straight Connector 12"/><p:cNvCxnSpPr/><p:nvPr/></p:nvCxnSpPr><p:spPr bwMode="auto"><a:xfrm><a:off x="1981200" y="1066800"/><a:ext cx="0" cy="3429000"/></a:xfrm><a:prstGeom prst="line"><a:avLst/></a:prstGeom><a:solidFill><a:schemeClr val="accent1"/></a:solidFill><a:ln w="9525" cap="flat" cmpd="sng" algn="ctr"><a:solidFill><a:schemeClr val="bg2"><a:lumMod val="75000"/></a:schemeClr></a:solidFill><a:prstDash val="dash"/><a:round/><a:headEnd type="none" w="med" len="med"/><a:tailEnd type="none" w="med" len="med"/></a:ln><a:effectLst/></p:spPr></p:cxnSp><p:cxnSp><p:nvCxnSpPr><p:cNvPr id="15" name="Straight Connector 14"/><p:cNvCxnSpPr/><p:nvPr/></p:nvCxnSpPr><p:spPr bwMode="auto"><a:xfrm><a:off x="2514600" y="1066800"/><a:ext cx="0" cy="3429000"/></a:xfrm><a:prstGeom prst="line"><a:avLst/></a:prstGeom><a:solidFill><a:schemeClr val="accent1"/></a:solidFill><a:ln w="9525" cap="flat" cmpd="sng" algn="ctr"><a:solidFill><a:schemeClr val="bg2"><a:lumMod val="75000"/></a:schemeClr></a:solidFill><a:prstDash val="dash"/><a:round/><a:headEnd type="none" w="med" len="med"/><a:tailEnd type="none" w="med" len="med"/></a:ln><a:effectLst/></p:spPr></p:cxnSp><p:cxnSp><p:nvCxnSpPr><p:cNvPr id="17" name="Straight Connector 16"/><p:cNvCxnSpPr/><p:nvPr/></p:nvCxnSpPr><p:spPr bwMode="auto"><a:xfrm><a:off x="3048000" y="1066800"/><a:ext cx="0" cy="3429000"/></a:xfrm><a:prstGeom prst="line"><a:avLst/></a:prstGeom><a:solidFill><a:schemeClr val="accent1"/></a:solidFill><a:ln w="9525" cap="flat" cmpd="sng" algn="ctr"><a:solidFill><a:schemeClr val="bg2"><a:lumMod val="75000"/></a:schemeClr></a:solidFill><a:prstDash val="dash"/><a:round/><a:headEnd type="none" w="med" len="med"/><a:tailEnd type="none" w="med" len="med"/></a:ln><a:effectLst/></p:spPr></p:cxnSp><p:cxnSp><p:nvCxnSpPr><p:cNvPr id="19" name="Straight Connector 18"/><p:cNvCxnSpPr/><p:nvPr/></p:nvCxnSpPr><p:spPr bwMode="auto"><a:xfrm><a:off x="3581400" y="1066800"/><a:ext cx="0" cy="3429000"/></a:xfrm><a:prstGeom prst="line"><a:avLst/></a:prstGeom><a:solidFill><a:schemeClr val="accent1"/></a:solidFill><a:ln w="9525" cap="flat" cmpd="sng" algn="ctr"><a:solidFill><a:schemeClr val="bg2"><a:lumMod val="75000"/></a:schemeClr></a:solidFill><a:prstDash val="dash"/><a:round/><a:headEnd type="none" w="med" len="med"/><a:tailEnd type="none" w="med" len="med"/></a:ln><a:effectLst/></p:spPr></p:cxnSp><p:cxnSp><p:nvCxnSpPr><p:cNvPr id="21" name="Straight Connector 20"/><p:cNvCxnSpPr/><p:nvPr/></p:nvCxnSpPr><p:spPr bwMode="auto"><a:xfrm><a:off x="4114800" y="1066800"/><a:ext cx="0" cy="3429000"/></a:xfrm><a:prstGeom prst="line"><a:avLst/></a:prstGeom><a:solidFill><a:schemeClr val="accent1"/></a:solidFill><a:ln w="9525" cap="flat" cmpd="sng" algn="ctr"><a:solidFill><a:schemeClr val="bg2"><a:lumMod val="75000"/></a:schemeClr></a:solidFill><a:prstDash val="dash"/><a:round/><a:headEnd type="none" w="med" len="med"/><a:tailEnd type="none" w="med" len="med"/></a:ln><a:effectLst/></p:spPr></p:cxnSp><p:cxnSp><p:nvCxnSpPr><p:cNvPr id="22" name="Straight Arrow Connector 21"/><p:cNvCxnSpPr/><p:nvPr/></p:nvCxnSpPr><p:spPr bwMode="auto"><a:xfrm rot="16200000"><a:off x="647700" y="3771900"/><a:ext cx="533400" cy="0"/></a:xfrm><a:prstGeom prst="straightConnector1"><a:avLst/></a:prstGeom><a:solidFill><a:schemeClr val="accent1"/></a:solidFill><a:ln w="38100" cap="flat" cmpd="sng" algn="ctr"><a:solidFill><a:srgbClr val="FF0000"/></a:solidFill><a:prstDash val="solid"/><a:round/><a:headEnd type="none" w="med" len="med"/><a:tailEnd type="triangle"/></a:ln><a:effectLst/></p:spPr></p:cxnSp><p:cxnSp><p:nvCxnSpPr><p:cNvPr id="24" name="Straight Connector 23"/><p:cNvCxnSpPr/><p:nvPr/></p:nvCxnSpPr><p:spPr bwMode="auto"><a:xfrm rot="5400000"><a:off x="2552700" y="1790700"/><a:ext cx="0" cy="3429000"/></a:xfrm><a:prstGeom prst="line"><a:avLst/></a:prstGeom><a:solidFill><a:schemeClr val="accent1"/></a:solidFill><a:ln w="9525" cap="flat" cmpd="sng" algn="ctr"><a:solidFill><a:schemeClr val="bg2"><a:lumMod val="75000"/></a:schemeClr></a:solidFill><a:prstDash val="dash"/><a:round/><a:headEnd type="none" w="med" len="med"/><a:tailEnd type="none" w="med" len="med"/></a:ln><a:effectLst/></p:spPr></p:cxnSp><p:cxnSp><p:nvCxnSpPr><p:cNvPr id="26" name="Straight Connector 25"/><p:cNvCxnSpPr/><p:nvPr/></p:nvCxnSpPr><p:spPr bwMode="auto"><a:xfrm rot="5400000"><a:off x="2552700" y="1257300"/><a:ext cx="0" cy="3429000"/></a:xfrm><a:prstGeom prst="line"><a:avLst/></a:prstGeom><a:solidFill><a:schemeClr val="accent1"/></a:solidFill><a:ln w="9525" cap="flat" cmpd="sng" algn="ctr"><a:solidFill><a:schemeClr val="bg2"><a:lumMod val="75000"/></a:schemeClr></a:solidFill><a:prstDash val="dash"/><a:round/><a:headEnd type="none" w="med" len="med"/><a:tailEnd type="none" w="med" len="med"/></a:ln><a:effectLst/></p:spPr></p:cxnSp><p:cxnSp><p:nvCxnSpPr><p:cNvPr id="28" name="Straight Connector 27"/><p:cNvCxnSpPr/><p:nvPr/></p:nvCxnSpPr><p:spPr bwMode="auto"><a:xfrm rot="5400000"><a:off x="2552700" y="723900"/><a:ext cx="0" cy="3429000"/></a:xfrm><a:prstGeom prst="line"><a:avLst/></a:prstGeom><a:solidFill><a:schemeClr val="accent1"/></a:solidFill><a:ln w="9525" cap="flat" cmpd="sng" algn="ctr"><a:solidFill><a:schemeClr val="bg2"><a:lumMod val="75000"/></a:schemeClr></a:solidFill><a:prstDash val="dash"/><a:round/><a:headEnd type="none" w="med" len="med"/><a:tailEnd type="none" w="med" len="med"/></a:ln><a:effectLst/></p:spPr></p:cxnSp><p:cxnSp><p:nvCxnSpPr><p:cNvPr id="30" name="Straight Connector 29"/><p:cNvCxnSpPr/><p:nvPr/></p:nvCxnSpPr><p:spPr bwMode="auto"><a:xfrm rot="5400000"><a:off x="2552700" y="190500"/><a:ext cx="0" cy="3429000"/></a:xfrm><a:prstGeom prst="line"><a:avLst/></a:prstGeom><a:solidFill><a:schemeClr val="accent1"/></a:solidFill><a:ln w="9525" cap="flat" cmpd="sng" algn="ctr"><a:solidFill><a:schemeClr val="bg2"><a:lumMod val="75000"/></a:schemeClr></a:solidFill><a:prstDash val="dash"/><a:round/><a:headEnd type="none" w="med" len="med"/><a:tailEnd type="none" w="med" len="med"/></a:ln><a:effectLst/></p:spPr></p:cxnSp><p:cxnSp><p:nvCxnSpPr><p:cNvPr id="32" name="Straight Connector 31"/><p:cNvCxnSpPr/><p:nvPr/></p:nvCxnSpPr><p:spPr bwMode="auto"><a:xfrm rot="5400000"><a:off x="2552700" y="-342899"/><a:ext cx="0" cy="3429000"/></a:xfrm><a:prstGeom prst="line"><a:avLst/></a:prstGeom><a:solidFill><a:schemeClr val="accent1"/></a:solidFill><a:ln w="9525" cap="flat" cmpd="sng" algn="ctr"><a:solidFill><a:schemeClr val="bg2"><a:lumMod val="75000"/></a:schemeClr></a:solidFill><a:prstDash val="dash"/><a:round/><a:headEnd type="none" w="med" len="med"/><a:tailEnd type="none" w="med" len="med"/></a:ln><a:effectLst/></p:spPr></p:cxnSp><p:cxnSp><p:nvCxnSpPr><p:cNvPr id="34" name="Straight Arrow Connector 33"/><p:cNvCxnSpPr/><p:nvPr/></p:nvCxnSpPr><p:spPr bwMode="auto"><a:xfrm flipV="1"><a:off x="2209800" y="2209800"/><a:ext cx="1066800" cy="571500"/></a:xfrm><a:prstGeom prst="straightConnector1"><a:avLst/></a:prstGeom><a:solidFill><a:schemeClr val="accent1"/></a:solidFill><a:ln w="38100" cap="flat" cmpd="sng" algn="ctr"><a:solidFill><a:schemeClr val="tx1"/></a:solidFill><a:prstDash val="solid"/><a:round/><a:headEnd type="none" w="med" len="med"/><a:tailEnd type="triangle"/></a:ln><a:effectLst/></p:spPr></p:cxnSp><p:cxnSp><p:nvCxnSpPr><p:cNvPr id="36" name="Straight Connector 35"/><p:cNvCxnSpPr/><p:nvPr/></p:nvCxnSpPr><p:spPr bwMode="auto"><a:xfrm><a:off x="2209800" y="2781300"/><a:ext cx="0" cy="1257300"/></a:xfrm><a:prstGeom prst="line"><a:avLst/></a:prstGeom><a:solidFill><a:schemeClr val="accent1"/></a:solidFill><a:ln w="9525" cap="flat" cmpd="sng" algn="ctr"><a:solidFill><a:schemeClr val="tx1"/></a:solidFill><a:prstDash val="solid"/><a:round/><a:headEnd type="none" w="med" len="med"/><a:tailEnd type="none" w="med" len="med"/></a:ln><a:effectLst/></p:spPr></p:cxnSp><p:cxnSp><p:nvCxnSpPr><p:cNvPr id="38" name="Straight Connector 37"/><p:cNvCxnSpPr/><p:nvPr/></p:nvCxnSpPr><p:spPr bwMode="auto"><a:xfrm><a:off x="3276600" y="2209800"/><a:ext cx="0" cy="1828800"/></a:xfrm><a:prstGeom prst="line"><a:avLst/></a:prstGeom><a:solidFill><a:schemeClr val="accent1"/></a:solidFill><a:ln w="9525" cap="flat" cmpd="sng" algn="ctr"><a:solidFill><a:schemeClr val="tx1"/></a:solidFill><a:prstDash val="solid"/><a:round/><a:headEnd type="none" w="med" len="med"/><a:tailEnd type="none" w="med" len="med"/></a:ln><a:effectLst/></p:spPr></p:cxnSp><p:cxnSp><p:nvCxnSpPr><p:cNvPr id="40" name="Straight Connector 39"/><p:cNvCxnSpPr/><p:nvPr/></p:nvCxnSpPr><p:spPr bwMode="auto"><a:xfrm flipH="1"><a:off x="914400" y="2781300"/><a:ext cx="1295400" cy="0"/></a:xfrm><a:prstGeom prst="line"><a:avLst/></a:prstGeom><a:solidFill><a:schemeClr val="accent1"/></a:solidFill><a:ln w="9525" cap="flat" cmpd="sng" algn="ctr"><a:solidFill><a:schemeClr val="tx1"/></a:solidFill><a:prstDash val="solid"/><a:round/><a:headEnd type="none" w="med" len="med"/><a:tailEnd type="none" w="med" len="med"/></a:ln><a:effectLst/></p:spPr></p:cxnSp><p:cxnSp><p:nvCxnSpPr><p:cNvPr id="42" name="Straight Connector 41"/><p:cNvCxnSpPr/><p:nvPr/></p:nvCxnSpPr><p:spPr bwMode="auto"><a:xfrm flipH="1"><a:off x="914400" y="2209800"/><a:ext cx="2362200" cy="0"/></a:xfrm><a:prstGeom prst="line"><a:avLst/></a:prstGeom><a:solidFill><a:schemeClr val="accent1"/></a:solidFill><a:ln w="9525" cap="flat" cmpd="sng" algn="ctr"><a:solidFill><a:schemeClr val="tx1"/></a:solidFill><a:prstDash val="solid"/><a:round/><a:headEnd type="none" w="med" len="med"/><a:tailEnd type="none" w="med" len="med"/></a:ln><a:effectLst/></p:spPr></p:cxnSp><p:sp><p:nvSpPr><p:cNvPr id="43" name="TextBox 42"/><p:cNvSpPr txBox="1"/><p:nvPr/></p:nvSpPr><p:spPr><a:xfrm><a:off x="4191000" y="3962400"/><a:ext cx="351378" cy="492443"/></a:xfrm><a:prstGeom prst="rect"><a:avLst/></a:prstGeom><a:noFill/></p:spPr><p:txBody><a:bodyPr wrap="none" rtlCol="0"><a:spAutoFit/></a:bodyPr><a:lstStyle/><a:p><a:r><a:rPr lang="en-US" dirty="0" smtClean="0"/><a:t>x</a:t></a:r><a:endParaRPr lang="en-US" dirty="0"/></a:p></p:txBody></p:sp><p:sp><p:nvSpPr><p:cNvPr id="44" name="TextBox 43"/><p:cNvSpPr txBox="1"/><p:nvPr/></p:nvSpPr><p:spPr><a:xfrm><a:off x="533400" y="3962400"/><a:ext cx="370614" cy="492443"/></a:xfrm><a:prstGeom prst="rect"><a:avLst/></a:prstGeom><a:noFill/></p:spPr><p:txBody><a:bodyPr wrap="none" rtlCol="0"><a:spAutoFit/></a:bodyPr><a:lstStyle/><a:p><a:r><a:rPr lang="en-US" dirty="0"/><a:t>0</a:t></a:r></a:p></p:txBody></p:sp><p:sp><p:nvSpPr><p:cNvPr id="45" name="TextBox 44"/><p:cNvSpPr txBox="1"/><p:nvPr/></p:nvSpPr><p:spPr><a:xfrm><a:off x="486822" y="879157"/><a:ext cx="351378" cy="492443"/></a:xfrm><a:prstGeom prst="rect"><a:avLst/></a:prstGeom><a:noFill/></p:spPr><p:txBody><a:bodyPr wrap="none" rtlCol="0"><a:spAutoFit/></a:bodyPr><a:lstStyle/><a:p><a:r><a:rPr lang="en-US" dirty="0"/><a:t>y</a:t></a:r></a:p></p:txBody></p:sp><p:sp><p:nvSpPr><p:cNvPr id="46" name="TextBox 45"/><p:cNvSpPr txBox="1"/><p:nvPr/></p:nvSpPr><p:spPr><a:xfrm><a:off x="2544222" y="2057400"/><a:ext cx="351378" cy="492443"/></a:xfrm><a:prstGeom prst="rect"><a:avLst/></a:prstGeom><a:noFill/></p:spPr><p:txBody><a:bodyPr wrap="none" rtlCol="0"><a:spAutoFit/></a:bodyPr><a:lstStyle/><a:p><a:r><a:rPr lang="en-US" dirty="0"/><a:t>v</a:t></a:r></a:p></p:txBody></p:sp><p:sp><p:nvSpPr><p:cNvPr id="47" name="TextBox 46"/><p:cNvSpPr txBox="1"/><p:nvPr/></p:nvSpPr><p:spPr><a:xfrm><a:off x="1154746" y="4003357"/><a:ext cx="234913" cy="492443"/></a:xfrm><a:prstGeom prst="rect"><a:avLst/></a:prstGeom><a:noFill/></p:spPr><p:txBody><a:bodyPr wrap="square" rtlCol="0"><a:spAutoFit/></a:bodyPr><a:lstStyle/><a:p><a:r><a:rPr lang="en-US" i="1" dirty="0" smtClean="0"/><a:t>i</a:t></a:r><a:endParaRPr lang="en-US" i="1" dirty="0"/></a:p></p:txBody></p:sp><p:sp><p:nvSpPr><p:cNvPr id="48" name="TextBox 47"/><p:cNvSpPr txBox="1"/><p:nvPr/></p:nvSpPr><p:spPr><a:xfrm><a:off x="533400" y="3276600"/><a:ext cx="258404" cy="492443"/></a:xfrm><a:prstGeom prst="rect"><a:avLst/></a:prstGeom><a:noFill/></p:spPr><p:txBody><a:bodyPr wrap="none" rtlCol="0"><a:spAutoFit/></a:bodyPr><a:lstStyle/><a:p><a:r><a:rPr lang="en-US" i="1" dirty="0" smtClean="0"/><a:t>j</a:t></a:r><a:endParaRPr lang="en-US" i="1" dirty="0"/></a:p></p:txBody></p:sp><p:cxnSp><p:nvCxnSpPr><p:cNvPr id="49" name="Straight Arrow Connector 48"/><p:cNvCxnSpPr/><p:nvPr/></p:nvCxnSpPr><p:spPr bwMode="auto"><a:xfrm rot="16200000"><a:off x="495300" y="2552700"/><a:ext cx="533400" cy="0"/></a:xfrm><a:prstGeom prst="straightConnector1"><a:avLst/></a:prstGeom><a:solidFill><a:schemeClr val="accent1"/></a:solidFill><a:ln w="38100" cap="flat" cmpd="sng" algn="ctr"><a:solidFill><a:srgbClr val="FF0000"/></a:solidFill><a:prstDash val="solid"/><a:round/><a:headEnd type="none" w="med" len="med"/><a:tailEnd type="triangle"/></a:ln><a:effectLst/></p:spPr></p:cxnSp><p:cxnSp><p:nvCxnSpPr><p:cNvPr id="50" name="Straight Arrow Connector 49"/><p:cNvCxnSpPr/><p:nvPr/></p:nvCxnSpPr><p:spPr bwMode="auto"><a:xfrm><a:off x="2209800" y="4191000"/><a:ext cx="533400" cy="0"/></a:xfrm><a:prstGeom prst="straightConnector1"><a:avLst/></a:prstGeom><a:solidFill><a:schemeClr val="accent1"/></a:solidFill><a:ln w="38100" cap="flat" cmpd="sng" algn="ctr"><a:solidFill><a:srgbClr val="FF0000"/></a:solidFill><a:prstDash val="solid"/><a:round/><a:headEnd type="none" w="med" len="med"/><a:tailEnd type="triangle"/></a:ln><a:effectLst/></p:spPr></p:cxnSp><p:cxnSp><p:nvCxnSpPr><p:cNvPr id="51" name="Straight Arrow Connector 50"/><p:cNvCxnSpPr/><p:nvPr/></p:nvCxnSpPr><p:spPr bwMode="auto"><a:xfrm><a:off x="2704011" y="4193178"/><a:ext cx="533400" cy="0"/></a:xfrm><a:prstGeom prst="straightConnector1"><a:avLst/></a:prstGeom><a:solidFill><a:schemeClr val="accent1"/></a:solidFill><a:ln w="38100" cap="flat" cmpd="sng" algn="ctr"><a:solidFill><a:srgbClr val="FF0000"/></a:solidFill><a:prstDash val="solid"/><a:round/><a:headEnd type="none" w="med" len="med"/><a:tailEnd type="triangle"/></a:ln><a:effectLst/></p:spPr></p:cxnSp><p:cxnSp><p:nvCxnSpPr><p:cNvPr id="52" name="Straight Arrow Connector 51"/><p:cNvCxnSpPr/><p:nvPr/></p:nvCxnSpPr><p:spPr bwMode="auto"><a:xfrm flipV="1"><a:off x="914400" y="2209800"/><a:ext cx="0" cy="585652"/></a:xfrm><a:prstGeom prst="straightConnector1"><a:avLst/></a:prstGeom><a:solidFill><a:schemeClr val="accent1"/></a:solidFill><a:ln w="38100" cap="flat" cmpd="sng" algn="ctr"><a:solidFill><a:srgbClr val="00B0F0"/></a:solidFill><a:prstDash val="solid"/><a:round/><a:headEnd type="none" w="med" len="med"/><a:tailEnd type="triangle"/></a:ln><a:effectLst/></p:spPr></p:cxnSp><p:cxnSp><p:nvCxnSpPr><p:cNvPr id="54" name="Straight Arrow Connector 53"/><p:cNvCxnSpPr/><p:nvPr/></p:nvCxnSpPr><p:spPr bwMode="auto"><a:xfrm><a:off x="2218507" y="4038600"/><a:ext cx="1058093" cy="0"/></a:xfrm><a:prstGeom prst="straightConnector1"><a:avLst/></a:prstGeom><a:solidFill><a:schemeClr val="accent1"/></a:solidFill><a:ln w="38100" cap="flat" cmpd="sng" algn="ctr"><a:solidFill><a:srgbClr val="00B0F0"/></a:solidFill><a:prstDash val="solid"/><a:round/><a:headEnd type="none" w="med" len="med"/><a:tailEnd type="triangle"/></a:ln><a:effectLst/></p:spPr></p:cxnSp><p:cxnSp><p:nvCxnSpPr><p:cNvPr id="56" name="Straight Arrow Connector 55"/><p:cNvCxnSpPr/><p:nvPr/></p:nvCxnSpPr><p:spPr bwMode="auto"><a:xfrm><a:off x="2240277" y="2780211"/><a:ext cx="1058093" cy="0"/></a:xfrm><a:prstGeom prst="straightConnector1"><a:avLst/></a:prstGeom><a:solidFill><a:schemeClr val="accent1"/></a:solidFill><a:ln w="38100" cap="flat" cmpd="sng" algn="ctr"><a:solidFill><a:srgbClr val="00B0F0"/></a:solidFill><a:prstDash val="solid"/><a:round/><a:headEnd type="none" w="med" len="med"/><a:tailEnd type="triangle"/></a:ln><a:effectLst/></p:spPr></p:cxnSp><p:cxnSp><p:nvCxnSpPr><p:cNvPr id="57" name="Straight Arrow Connector 56"/><p:cNvCxnSpPr/><p:nvPr/></p:nvCxnSpPr><p:spPr bwMode="auto"><a:xfrm flipV="1"><a:off x="2209800" y="2170611"/><a:ext cx="0" cy="585652"/></a:xfrm><a:prstGeom prst="straightConnector1"><a:avLst/></a:prstGeom><a:solidFill><a:schemeClr val="accent1"/></a:solidFill><a:ln w="38100" cap="flat" cmpd="sng" algn="ctr"><a:solidFill><a:srgbClr val="00B0F0"/></a:solidFill><a:prstDash val="solid"/><a:round/><a:headEnd type="none" w="med" len="med"/><a:tailEnd type="triangle"/></a:ln><a:effectLst/></p:spPr></p:cxnSp><p:sp><p:nvSpPr><p:cNvPr id="58" name="TextBox 57"/><p:cNvSpPr txBox="1"/><p:nvPr/></p:nvSpPr><p:spPr><a:xfrm><a:off x="1828800" y="2209800"/><a:ext cx="370614" cy="492443"/></a:xfrm><a:prstGeom prst="rect"><a:avLst/></a:prstGeom><a:noFill/></p:spPr><p:txBody><a:bodyPr wrap="none" rtlCol="0"><a:spAutoFit/></a:bodyPr><a:lstStyle/><a:p><a:r><a:rPr lang="en-US" dirty="0" smtClean="0"/><a:t>b</a:t></a:r><a:endParaRPr lang="en-US" dirty="0"/></a:p></p:txBody></p:sp><p:sp><p:nvSpPr><p:cNvPr id="59" name="TextBox 58"/><p:cNvSpPr txBox="1"/><p:nvPr/></p:nvSpPr><p:spPr><a:xfrm><a:off x="2590800" y="2707957"/><a:ext cx="370614" cy="492443"/></a:xfrm><a:prstGeom prst="rect"><a:avLst/></a:prstGeom><a:noFill/></p:spPr><p:txBody><a:bodyPr wrap="none" rtlCol="0"><a:spAutoFit/></a:bodyPr><a:lstStyle/><a:p><a:r><a:rPr lang="en-US" dirty="0" smtClean="0"/><a:t>a</a:t></a:r><a:endParaRPr lang="en-US" dirty="0"/></a:p></p:txBody></p:sp><p:cxnSp><p:nvCxnSpPr><p:cNvPr id="60" name="Straight Arrow Connector 59"/><p:cNvCxnSpPr/><p:nvPr/></p:nvCxnSpPr><p:spPr bwMode="auto"><a:xfrm><a:off x="5211222" y="4038600"/><a:ext cx="3810000" cy="0"/></a:xfrm><a:prstGeom prst="straightConnector1"><a:avLst/></a:prstGeom><a:solidFill><a:schemeClr val="accent1"/></a:solidFill><a:ln w="44450" cap="flat" cmpd="sng" algn="ctr"><a:solidFill><a:schemeClr val="tx1"/></a:solidFill><a:prstDash val="solid"/><a:round/><a:headEnd type="none" w="med" len="med"/><a:tailEnd type="triangle"/></a:ln><a:effectLst/></p:spPr></p:cxnSp><p:cxnSp><p:nvCxnSpPr><p:cNvPr id="61" name="Straight Arrow Connector 60"/><p:cNvCxnSpPr/><p:nvPr/></p:nvCxnSpPr><p:spPr bwMode="auto"><a:xfrm flipV="1"><a:off x="5668422" y="1066800"/><a:ext cx="0" cy="3429000"/></a:xfrm><a:prstGeom prst="straightConnector1"><a:avLst/></a:prstGeom><a:solidFill><a:schemeClr val="accent1"/></a:solidFill><a:ln w="44450" cap="flat" cmpd="sng" algn="ctr"><a:solidFill><a:schemeClr val="tx1"/></a:solidFill><a:prstDash val="solid"/><a:round/><a:headEnd type="none" w="med" len="med"/><a:tailEnd type="triangle"/></a:ln><a:effectLst/></p:spPr></p:cxnSp><p:cxnSp><p:nvCxnSpPr><p:cNvPr id="62" name="Straight Arrow Connector 61"/><p:cNvCxnSpPr/><p:nvPr/></p:nvCxnSpPr><p:spPr bwMode="auto"><a:xfrm><a:off x="5668422" y="4038600"/><a:ext cx="533400" cy="0"/></a:xfrm><a:prstGeom prst="straightConnector1"><a:avLst/></a:prstGeom><a:solidFill><a:schemeClr val="accent1"/></a:solidFill><a:ln w="38100" cap="flat" cmpd="sng" algn="ctr"><a:solidFill><a:srgbClr val="FF0000"/></a:solidFill><a:prstDash val="solid"/><a:round/><a:headEnd type="none" w="med" len="med"/><a:tailEnd type="triangle"/></a:ln><a:effectLst/></p:spPr></p:cxnSp><p:cxnSp><p:nvCxnSpPr><p:cNvPr id="63" name="Straight Connector 62"/><p:cNvCxnSpPr/><p:nvPr/></p:nvCxnSpPr><p:spPr bwMode="auto"><a:xfrm><a:off x="6201822" y="1066800"/><a:ext cx="0" cy="3429000"/></a:xfrm><a:prstGeom prst="line"><a:avLst/></a:prstGeom><a:solidFill><a:schemeClr val="accent1"/></a:solidFill><a:ln w="9525" cap="flat" cmpd="sng" algn="ctr"><a:solidFill><a:schemeClr val="bg2"><a:lumMod val="75000"/></a:schemeClr></a:solidFill><a:prstDash val="dash"/><a:round/><a:headEnd type="none" w="med" len="med"/><a:tailEnd type="none" w="med" len="med"/></a:ln><a:effectLst/></p:spPr></p:cxnSp><p:cxnSp><p:nvCxnSpPr><p:cNvPr id="64" name="Straight Connector 63"/><p:cNvCxnSpPr/><p:nvPr/></p:nvCxnSpPr><p:spPr bwMode="auto"><a:xfrm><a:off x="6735222" y="1066800"/><a:ext cx="0" cy="3429000"/></a:xfrm><a:prstGeom prst="line"><a:avLst/></a:prstGeom><a:solidFill><a:schemeClr val="accent1"/></a:solidFill><a:ln w="9525" cap="flat" cmpd="sng" algn="ctr"><a:solidFill><a:schemeClr val="bg2"><a:lumMod val="75000"/></a:schemeClr></a:solidFill><a:prstDash val="dash"/><a:round/><a:headEnd type="none" w="med" len="med"/><a:tailEnd type="none" w="med" len="med"/></a:ln><a:effectLst/></p:spPr></p:cxnSp><p:cxnSp><p:nvCxnSpPr><p:cNvPr id="65" name="Straight Connector 64"/><p:cNvCxnSpPr/><p:nvPr/></p:nvCxnSpPr><p:spPr bwMode="auto"><a:xfrm><a:off x="7268622" y="1066800"/><a:ext cx="0" cy="3429000"/></a:xfrm><a:prstGeom prst="line"><a:avLst/></a:prstGeom><a:solidFill><a:schemeClr val="accent1"/></a:solidFill><a:ln w="9525" cap="flat" cmpd="sng" algn="ctr"><a:solidFill><a:schemeClr val="bg2"><a:lumMod val="75000"/></a:schemeClr></a:solidFill><a:prstDash val="dash"/><a:round/><a:headEnd type="none" w="med" len="med"/><a:tailEnd type="none" w="med" len="med"/></a:ln><a:effectLst/></p:spPr></p:cxnSp><p:cxnSp><p:nvCxnSpPr><p:cNvPr id="66" name="Straight Connector 65"/><p:cNvCxnSpPr/><p:nvPr/></p:nvCxnSpPr><p:spPr bwMode="auto"><a:xfrm><a:off x="7802022" y="1066800"/><a:ext cx="0" cy="3429000"/></a:xfrm><a:prstGeom prst="line"><a:avLst/></a:prstGeom><a:solidFill><a:schemeClr val="accent1"/></a:solidFill><a:ln w="9525" cap="flat" cmpd="sng" algn="ctr"><a:solidFill><a:schemeClr val="bg2"><a:lumMod val="75000"/></a:schemeClr></a:solidFill><a:prstDash val="dash"/><a:round/><a:headEnd type="none" w="med" len="med"/><a:tailEnd type="none" w="med" len="med"/></a:ln><a:effectLst/></p:spPr></p:cxnSp><p:cxnSp><p:nvCxnSpPr><p:cNvPr id="67" name="Straight Connector 66"/><p:cNvCxnSpPr/><p:nvPr/></p:nvCxnSpPr><p:spPr bwMode="auto"><a:xfrm><a:off x="8335422" y="1066800"/><a:ext cx="0" cy="3429000"/></a:xfrm><a:prstGeom prst="line"><a:avLst/></a:prstGeom><a:solidFill><a:schemeClr val="accent1"/></a:solidFill><a:ln w="9525" cap="flat" cmpd="sng" algn="ctr"><a:solidFill><a:schemeClr val="bg2"><a:lumMod val="75000"/></a:schemeClr></a:solidFill><a:prstDash val="dash"/><a:round/><a:headEnd type="none" w="med" len="med"/><a:tailEnd type="none" w="med" len="med"/></a:ln><a:effectLst/></p:spPr></p:cxnSp><p:cxnSp><p:nvCxnSpPr><p:cNvPr id="68" name="Straight Connector 67"/><p:cNvCxnSpPr/><p:nvPr/></p:nvCxnSpPr><p:spPr bwMode="auto"><a:xfrm><a:off x="8868822" y="1066800"/><a:ext cx="0" cy="3429000"/></a:xfrm><a:prstGeom prst="line"><a:avLst/></a:prstGeom><a:solidFill><a:schemeClr val="accent1"/></a:solidFill><a:ln w="9525" cap="flat" cmpd="sng" algn="ctr"><a:solidFill><a:schemeClr val="bg2"><a:lumMod val="75000"/></a:schemeClr></a:solidFill><a:prstDash val="dash"/><a:round/><a:headEnd type="none" w="med" len="med"/><a:tailEnd type="none" w="med" len="med"/></a:ln><a:effectLst/></p:spPr></p:cxnSp><p:cxnSp><p:nvCxnSpPr><p:cNvPr id="69" name="Straight Arrow Connector 68"/><p:cNvCxnSpPr/><p:nvPr/></p:nvCxnSpPr><p:spPr bwMode="auto"><a:xfrm rot="16200000"><a:off x="5401722" y="3771900"/><a:ext cx="533400" cy="0"/></a:xfrm><a:prstGeom prst="straightConnector1"><a:avLst/></a:prstGeom><a:solidFill><a:schemeClr val="accent1"/></a:solidFill><a:ln w="38100" cap="flat" cmpd="sng" algn="ctr"><a:solidFill><a:srgbClr val="FF0000"/></a:solidFill><a:prstDash val="solid"/><a:round/><a:headEnd type="none" w="med" len="med"/><a:tailEnd type="triangle"/></a:ln><a:effectLst/></p:spPr></p:cxnSp><p:cxnSp><p:nvCxnSpPr><p:cNvPr id="70" name="Straight Connector 69"/><p:cNvCxnSpPr/><p:nvPr/></p:nvCxnSpPr><p:spPr bwMode="auto"><a:xfrm rot="5400000"><a:off x="7306722" y="1790700"/><a:ext cx="0" cy="3429000"/></a:xfrm><a:prstGeom prst="line"><a:avLst/></a:prstGeom><a:solidFill><a:schemeClr val="accent1"/></a:solidFill><a:ln w="9525" cap="flat" cmpd="sng" algn="ctr"><a:solidFill><a:schemeClr val="bg2"><a:lumMod val="75000"/></a:schemeClr></a:solidFill><a:prstDash val="dash"/><a:round/><a:headEnd type="none" w="med" len="med"/><a:tailEnd type="none" w="med" len="med"/></a:ln><a:effectLst/></p:spPr></p:cxnSp><p:cxnSp><p:nvCxnSpPr><p:cNvPr id="71" name="Straight Connector 70"/><p:cNvCxnSpPr/><p:nvPr/></p:nvCxnSpPr><p:spPr bwMode="auto"><a:xfrm rot="5400000"><a:off x="7306722" y="1257300"/><a:ext cx="0" cy="3429000"/></a:xfrm><a:prstGeom prst="line"><a:avLst/></a:prstGeom><a:solidFill><a:schemeClr val="accent1"/></a:solidFill><a:ln w="9525" cap="flat" cmpd="sng" algn="ctr"><a:solidFill><a:schemeClr val="bg2"><a:lumMod val="75000"/></a:schemeClr></a:solidFill><a:prstDash val="dash"/><a:round/><a:headEnd type="none" w="med" len="med"/><a:tailEnd type="none" w="med" len="med"/></a:ln><a:effectLst/></p:spPr></p:cxnSp><p:cxnSp><p:nvCxnSpPr><p:cNvPr id="72" name="Straight Connector 71"/><p:cNvCxnSpPr/><p:nvPr/></p:nvCxnSpPr><p:spPr bwMode="auto"><a:xfrm rot="5400000"><a:off x="7306722" y="723900"/><a:ext cx="0" cy="3429000"/></a:xfrm><a:prstGeom prst="line"><a:avLst/></a:prstGeom><a:solidFill><a:schemeClr val="accent1"/></a:solidFill><a:ln w="9525" cap="flat" cmpd="sng" algn="ctr"><a:solidFill><a:schemeClr val="bg2"><a:lumMod val="75000"/></a:schemeClr></a:solidFill><a:prstDash val="dash"/><a:round/><a:headEnd type="none" w="med" len="med"/><a:tailEnd type="none" w="med" len="med"/></a:ln><a:effectLst/></p:spPr></p:cxnSp><p:cxnSp><p:nvCxnSpPr><p:cNvPr id="73" name="Straight Connector 72"/><p:cNvCxnSpPr/><p:nvPr/></p:nvCxnSpPr><p:spPr bwMode="auto"><a:xfrm rot="5400000"><a:off x="7306722" y="190500"/><a:ext cx="0" cy="3429000"/></a:xfrm><a:prstGeom prst="line"><a:avLst/></a:prstGeom><a:solidFill><a:schemeClr val="accent1"/></a:solidFill><a:ln w="9525" cap="flat" cmpd="sng" algn="ctr"><a:solidFill><a:schemeClr val="bg2"><a:lumMod val="75000"/></a:schemeClr></a:solidFill><a:prstDash val="dash"/><a:round/><a:headEnd type="none" w="med" len="med"/><a:tailEnd type="none" w="med" len="med"/></a:ln><a:effectLst/></p:spPr></p:cxnSp><p:cxnSp><p:nvCxnSpPr><p:cNvPr id="74" name="Straight Connector 73"/><p:cNvCxnSpPr/><p:nvPr/></p:nvCxnSpPr><p:spPr bwMode="auto"><a:xfrm rot="5400000"><a:off x="7306722" y="-342899"/><a:ext cx="0" cy="3429000"/></a:xfrm><a:prstGeom prst="line"><a:avLst/></a:prstGeom><a:solidFill><a:schemeClr val="accent1"/></a:solidFill><a:ln w="9525" cap="flat" cmpd="sng" algn="ctr"><a:solidFill><a:schemeClr val="bg2"><a:lumMod val="75000"/></a:schemeClr></a:solidFill><a:prstDash val="dash"/><a:round/><a:headEnd type="none" w="med" len="med"/><a:tailEnd type="none" w="med" len="med"/></a:ln><a:effectLst/></p:spPr></p:cxnSp><p:cxnSp><p:nvCxnSpPr><p:cNvPr id="77" name="Straight Connector 76"/><p:cNvCxnSpPr/><p:nvPr/></p:nvCxnSpPr><p:spPr bwMode="auto"><a:xfrm><a:off x="7686903" y="2057400"/><a:ext cx="9297" cy="1945957"/></a:xfrm><a:prstGeom prst="line"><a:avLst/></a:prstGeom><a:solidFill><a:schemeClr val="accent1"/></a:solidFill><a:ln w="9525" cap="flat" cmpd="sng" algn="ctr"><a:solidFill><a:schemeClr val="tx1"/></a:solidFill><a:prstDash val="solid"/><a:round/><a:headEnd type="none" w="med" len="med"/><a:tailEnd type="none" w="med" len="med"/></a:ln><a:effectLst/></p:spPr></p:cxnSp><p:cxnSp><p:nvCxnSpPr><p:cNvPr id="79" name="Straight Connector 78"/><p:cNvCxnSpPr/><p:nvPr/></p:nvCxnSpPr><p:spPr bwMode="auto"><a:xfrm flipH="1"><a:off x="5629233" y="2057400"/><a:ext cx="2056311" cy="0"/></a:xfrm><a:prstGeom prst="line"><a:avLst/></a:prstGeom><a:solidFill><a:schemeClr val="accent1"/></a:solidFill><a:ln w="9525" cap="flat" cmpd="sng" algn="ctr"><a:solidFill><a:schemeClr val="tx1"/></a:solidFill><a:prstDash val="solid"/><a:round/><a:headEnd type="none" w="med" len="med"/><a:tailEnd type="none" w="med" len="med"/></a:ln><a:effectLst/></p:spPr></p:cxnSp><p:sp><p:nvSpPr><p:cNvPr id="80" name="TextBox 79"/><p:cNvSpPr txBox="1"/><p:nvPr/></p:nvSpPr><p:spPr><a:xfrm><a:off x="8945022" y="3962400"/><a:ext cx="351378" cy="492443"/></a:xfrm><a:prstGeom prst="rect"><a:avLst/></a:prstGeom><a:noFill/></p:spPr><p:txBody><a:bodyPr wrap="none" rtlCol="0"><a:spAutoFit/></a:bodyPr><a:lstStyle/><a:p><a:r><a:rPr lang="en-US" dirty="0" smtClean="0"/><a:t>x</a:t></a:r><a:endParaRPr lang="en-US" dirty="0"/></a:p></p:txBody></p:sp><p:sp><p:nvSpPr><p:cNvPr id="81" name="TextBox 80"/><p:cNvSpPr txBox="1"/><p:nvPr/></p:nvSpPr><p:spPr><a:xfrm><a:off x="5287422" y="3962400"/><a:ext cx="370614" cy="492443"/></a:xfrm><a:prstGeom prst="rect"><a:avLst/></a:prstGeom><a:noFill/></p:spPr><p:txBody><a:bodyPr wrap="none" rtlCol="0"><a:spAutoFit/></a:bodyPr><a:lstStyle/><a:p><a:r><a:rPr lang="en-US" dirty="0"/><a:t>0</a:t></a:r></a:p></p:txBody></p:sp><p:sp><p:nvSpPr><p:cNvPr id="82" name="TextBox 81"/><p:cNvSpPr txBox="1"/><p:nvPr/></p:nvSpPr><p:spPr><a:xfrm><a:off x="7467600" y="1564957"/><a:ext cx="407484" cy="492443"/></a:xfrm><a:prstGeom prst="rect"><a:avLst/></a:prstGeom><a:noFill/></p:spPr><p:txBody><a:bodyPr wrap="none" rtlCol="0"><a:spAutoFit/></a:bodyPr><a:lstStyle/><a:p><a:r><a:rPr lang="en-US" dirty="0" smtClean="0"/><a:t>P</a:t></a:r><a:endParaRPr lang="en-US" dirty="0"/></a:p></p:txBody></p:sp><p:sp><p:nvSpPr><p:cNvPr id="83" name="TextBox 82"/><p:cNvSpPr txBox="1"/><p:nvPr/></p:nvSpPr><p:spPr><a:xfrm><a:off x="5908768" y="4003357"/><a:ext cx="234913" cy="492443"/></a:xfrm><a:prstGeom prst="rect"><a:avLst/></a:prstGeom><a:noFill/></p:spPr><p:txBody><a:bodyPr wrap="square" rtlCol="0"><a:spAutoFit/></a:bodyPr><a:lstStyle/><a:p><a:r><a:rPr lang="en-US" i="1" dirty="0" smtClean="0"/><a:t>i</a:t></a:r><a:endParaRPr lang="en-US" i="1" dirty="0"/></a:p></p:txBody></p:sp><p:sp><p:nvSpPr><p:cNvPr id="84" name="TextBox 83"/><p:cNvSpPr txBox="1"/><p:nvPr/></p:nvSpPr><p:spPr><a:xfrm><a:off x="5287422" y="3276600"/><a:ext cx="258404" cy="492443"/></a:xfrm><a:prstGeom prst="rect"><a:avLst/></a:prstGeom><a:noFill/></p:spPr><p:txBody><a:bodyPr wrap="none" rtlCol="0"><a:spAutoFit/></a:bodyPr><a:lstStyle/><a:p><a:r><a:rPr lang="en-US" i="1" dirty="0" smtClean="0"/><a:t>j</a:t></a:r><a:endParaRPr lang="en-US" i="1" dirty="0"/></a:p></p:txBody></p:sp><p:cxnSp><p:nvCxnSpPr><p:cNvPr id="88" name="Straight Arrow Connector 87"/><p:cNvCxnSpPr/><p:nvPr/></p:nvCxnSpPr><p:spPr bwMode="auto"><a:xfrm flipH="1" flipV="1"><a:off x="5472729" y="2092643"/><a:ext cx="13671" cy="1945957"/></a:xfrm><a:prstGeom prst="straightConnector1"><a:avLst/></a:prstGeom><a:solidFill><a:schemeClr val="accent1"/></a:solidFill><a:ln w="38100" cap="flat" cmpd="sng" algn="ctr"><a:solidFill><a:srgbClr val="00B0F0"/></a:solidFill><a:prstDash val="solid"/><a:round/><a:headEnd type="none" w="med" len="med"/><a:tailEnd type="triangle"/></a:ln><a:effectLst/></p:spPr></p:cxnSp><p:cxnSp><p:nvCxnSpPr><p:cNvPr id="89" name="Straight Arrow Connector 88"/><p:cNvCxnSpPr/><p:nvPr/></p:nvCxnSpPr><p:spPr bwMode="auto"><a:xfrm><a:off x="5638800" y="4419600"/><a:ext cx="2124033" cy="0"/></a:xfrm><a:prstGeom prst="straightConnector1"><a:avLst/></a:prstGeom><a:solidFill><a:schemeClr val="accent1"/></a:solidFill><a:ln w="38100" cap="flat" cmpd="sng" algn="ctr"><a:solidFill><a:srgbClr val="00B0F0"/></a:solidFill><a:prstDash val="solid"/><a:round/><a:headEnd type="none" w="med" len="med"/><a:tailEnd type="triangle"/></a:ln><a:effectLst/></p:spPr></p:cxnSp><p:sp><p:nvSpPr><p:cNvPr id="92" name="TextBox 91"/><p:cNvSpPr txBox="1"/><p:nvPr/></p:nvSpPr><p:spPr><a:xfrm><a:off x="5039586" y="1945957"/><a:ext cx="370614" cy="492443"/></a:xfrm><a:prstGeom prst="rect"><a:avLst/></a:prstGeom><a:noFill/></p:spPr><p:txBody><a:bodyPr wrap="none" rtlCol="0"><a:spAutoFit/></a:bodyPr><a:lstStyle/><a:p><a:r><a:rPr lang="en-US" dirty="0" smtClean="0"/><a:t>b</a:t></a:r><a:endParaRPr lang="en-US" dirty="0"/></a:p></p:txBody></p:sp><p:sp><p:nvSpPr><p:cNvPr id="93" name="TextBox 92"/><p:cNvSpPr txBox="1"/><p:nvPr/></p:nvSpPr><p:spPr><a:xfrm><a:off x="7477986" y="4343400"/><a:ext cx="370614" cy="492443"/></a:xfrm><a:prstGeom prst="rect"><a:avLst/></a:prstGeom><a:noFill/></p:spPr><p:txBody><a:bodyPr wrap="none" rtlCol="0"><a:spAutoFit/></a:bodyPr><a:lstStyle/><a:p><a:r><a:rPr lang="en-US" dirty="0" smtClean="0"/><a:t>a</a:t></a:r><a:endParaRPr lang="en-US" dirty="0"/></a:p></p:txBody></p:sp><p:cxnSp><p:nvCxnSpPr><p:cNvPr id="101" name="Straight Arrow Connector 100"/><p:cNvCxnSpPr><a:endCxn id="82" idx="2"/></p:cNvCxnSpPr><p:nvPr/></p:nvCxnSpPr><p:spPr bwMode="auto"><a:xfrm flipV="1"><a:off x="5675811" y="2057400"/><a:ext cx="1995531" cy="1981200"/></a:xfrm><a:prstGeom prst="straightConnector1"><a:avLst/></a:prstGeom><a:solidFill><a:schemeClr val="accent1"/></a:solidFill><a:ln w="38100" cap="flat" cmpd="sng" algn="ctr"><a:solidFill><a:schemeClr val="tx1"/></a:solidFill><a:prstDash val="solid"/><a:round/><a:headEnd type="none" w="med" len="med"/><a:tailEnd type="triangle"/></a:ln><a:effectLst/></p:spPr></p:cxnSp></p:spTree><p:extLst><p:ext uri="{BB962C8B-B14F-4D97-AF65-F5344CB8AC3E}"><p14:creationId xmlns:p14="http://schemas.microsoft.com/office/powerpoint/2010/main" val="3170436479"/></p:ext></p:extLst></p:cSld><p:clrMapOvr><a:masterClrMapping/></p:clrMapOvr><mc:AlternateContent xmlns:mc="http://schemas.openxmlformats.org/markup-compatibility/2006" xmlns:p14="http://schemas.microsoft.com/office/powerpoint/2010/main"><mc:Choice Requires="p14"><p:transition spd="slow" p14:dur="2000" advTm="187796"/></mc:Choice><mc:Fallback xmlns=""><p:transition spd="slow" advTm="187796"/></mc:Fallback></mc:AlternateContent><p:timing><p:tnLst><p:par><p:cTn id="1" dur="indefinite" restart="never" nodeType="tmRoot"/></p:par></p:tnLst></p:timing></p:sld>